ArithmeticOptimizer/__init__.py
ArithmeticOptimizer-0.0.1.dist-info/LICENSE.txt
ArithmeticOptimizer-0.0.1.dist-info/METADATA
ArithmeticOptimizer-0.0.1.dist-info/WHEEL
ArithmeticOptimizer-0.0.1.dist-info/top_level.txt
ArithmeticOptimizer-0.0.1.dist-info/RECORD
